fugue_bigquery/__init__.py
fugue_bigquery/_constants.py
fugue_bigquery/_utils.py
fugue_bigquery/api.py
fugue_bigquery/client.py
fugue_bigquery/dataframe.py
fugue_bigquery/execution_engine.py
fugue_bigquery/ray_execution_engine.py
fugue_bigquery/registry.py
fugue_bigquery/whylogs.py
fugue_bigquery_version/__init__.py
fugue_trino/__init__.py
fugue_trino/_constants.py
fugue_trino/_utils.py
fugue_trino/client.py
fugue_trino/dataframe.py
fugue_trino/execution_engine.py
fugue_trino/registry.py
fugue_trino/ibis_trino/__init__.py
fugue_trino/ibis_trino/backend.py
tests/__init__.py
tests/fugue_bigquery/__init__.py
tests/fugue_bigquery/mock_engine.py
tests/fugue_bigquery/test_dataframe.py
tests/fugue_bigquery/test_execution_engine.py
tests/fugue_bigquery/test_workflow.py
fugue_bigquery-0.0.1.dist-info/LICENSE
fugue_bigquery-0.0.1.dist-info/METADATA
fugue_bigquery-0.0.1.dist-info/WHEEL
fugue_bigquery-0.0.1.dist-info/entry_points.txt
fugue_bigquery-0.0.1.dist-info/top_level.txt
fugue_bigquery-0.0.1.dist-info/RECORD
